{
  "openapi": "3.0.0",
  "paths": {
    "/accounts/{customerId}/summary": {
      "get": {
        "operationId": "AccountsController_getAccountSummary",
        "parameters": [
          {
            "name": "customerId",
            "required": true,
            "in": "path",
            "schema": {
              "type": "string"
            }
          }
        ],
        "responses": {
          "200": {
            "description": ""
          }
        },
        "tags": [
          "Accounts"
        ]
      }
    },
    "/auth/login": {
      "post": {
        "operationId": "AuthController_login",
        "parameters": [],
        "responses": {
          "200": {
            "description": "Login realizado com sucesso"
          },
          "401": {
            "description": "Credenciais inválidas"
          }
        },
        "summary": "Login de usuário",
        "tags": [
          "Auth"
        ]
      }
    },
    "/auth/register": {
      "post": {
        "operationId": "AuthController_register",
        "parameters": [],
        "requestBody": {
          "required": true,
          "content": {
            "application/json": {
              "schema": {
                "$ref": "#/components/schemas/RegisterDto"
              }
            }
          }
        },
        "responses": {
          "201": {
            "description": "Usuário criado com sucesso"
          },
          "400": {
            "description": "Dados inválidos"
          }
        },
        "summary": "Registrar novo usuário",
        "tags": [
          "Auth"
        ]
      }
    },
    "/auth/forgot": {
      "post": {
        "operationId": "AuthController_forgot",
        "parameters": [],
        "requestBody": {
          "required": true,
          "content": {
            "application/json": {
              "schema": {
                "$ref": "#/components/schemas/ForgotPasswordDto"
              }
            }
          }
        },
        "responses": {
          "200": {
            "description": "E-mail de recuperação enviado"
          }
        },
        "summary": "Solicitar redefinição de senha",
        "tags": [
          "Auth"
        ]
      }
    },
    "/auth/reset": {
      "post": {
        "operationId": "AuthController_reset",
        "parameters": [],
        "requestBody": {
          "required": true,
          "content": {
            "application/json": {
              "schema": {
                "$ref": "#/components/schemas/ResetPasswordDto"
              }
            }
          }
        },
        "responses": {
          "200": {
            "description": "Senha redefinida com sucesso"
          }
        },
        "summary": "Redefinir senha com token",
        "tags": [
          "Auth"
        ]
      }
    },
    "/auth/me": {
      "get": {
        "operationId": "AuthController_me",
        "parameters": [],
        "responses": {
          "200": {
            "description": "Dados do usuário"
          },
          "401": {
            "description": "Não autenticado"
          }
        },
        "security": [
          {
            "JWT-auth": []
          }
        ],
        "summary": "Obter dados do usuário autenticado",
        "tags": [
          "Auth"
        ]
      }
    },
    "/users": {
      "get": {
        "operationId": "UsersController_list",
        "parameters": [],
        "responses": {
          "200": {
            "description": ""
          }
        },
        "tags": [
          "Users"
        ]
      }
    },
    "/users/{id}": {
      "patch": {
        "operationId": "UsersController_update",
        "parameters": [
          {
            "name": "id",
            "required": true,
            "in": "path",
            "schema": {
              "type": "string"
            }
          }
        ],
        "requestBody": {
          "required": true,
          "content": {
            "application/json": {
              "schema": {
                "$ref": "#/components/schemas/UpdateUserDto"
              }
            }
          }
        },
        "responses": {
          "200": {
            "description": ""
          }
        },
        "tags": [
          "Users"
        ]
      }
    },
    "/users/{id}/password": {
      "patch": {
        "operationId": "UsersController_changePassword",
        "parameters": [
          {
            "name": "id",
            "required": true,
            "in": "path",
            "schema": {
              "type": "string"
            }
          }
        ],
        "requestBody": {
          "required": true,
          "content": {
            "application/json": {
              "schema": {
                "$ref": "#/components/schemas/ChangePasswordDto"
              }
            }
          }
        },
        "responses": {
          "200": {
            "description": ""
          }
        },
        "tags": [
          "Users"
        ]
      }
    },
    "/customers": {
      "get": {
        "operationId": "CustomersController_list",
        "parameters": [
          {
            "name": "page",
            "required": false,
            "in": "query",
            "schema": {
              "minimum": 1,
              "example": 1,
              "type": "number"
            }
          },
          {
            "name": "limit",
            "required": false,
            "in": "query",
            "schema": {
              "minimum": 1,
              "maximum": 100,
              "example": 20,
              "type": "number"
            }
          },
          {
            "name": "search",
            "required": false,
            "in": "query",
            "schema": {
              "example": "João",
              "type": "string"
            }
          },
          {
            "name": "type",
            "required": false,
            "in": "query",
            "schema": {
              "type": "string",
              "enum": [
                "PF",
                "PJ"
              ]
            }
          },
          {
            "name": "status",
            "required": false,
            "in": "query",
            "schema": {
              "type": "string",
              "enum": [
                "not_requested",
                "requested",
                "in_review",
                "approved",
                "rejected",
                "suspended"
              ]
            }
          },
          {
            "name": "cpf",
            "required": false,
            "in": "query",
            "schema": {
              "example": "12345678901",
              "type": "string"
            }
          },
          {
            "name": "cnpj",
            "required": false,
            "in": "query",
            "schema": {
              "example": "12345678000190",
              "type": "string"
            }
          },
          {
            "name": "email",
            "required": false,
            "in": "query",
            "schema": {
              "example": "joao@email.com",
              "type": "string"
            }
          }
        ],
        "responses": {
          "200": {
            "description": ""
          }
        },
        "security": [
          {
            "bearer": []
          }
        ],
        "summary": "Listar customers",
        "tags": [
          "Customers"
        ]
      },
      "post": {
        "operationId": "CustomersController_create",
        "parameters": [],
        "requestBody": {
          "required": true,
          "content": {
            "application/json": {
              "schema": {
                "$ref": "#/components/schemas/CreateCustomerLocalDto"
              }
            }
          }
        },
        "responses": {
          "201": {
            "description": ""
          }
        },
        "security": [
          {
            "bearer": []
          }
        ],
        "summary": "Criar customer",
        "tags": [
          "Customers"
        ]
      }
    },
    "/customers/me": {
      "get": {
        "operationId": "CustomersController_me",
        "parameters": [],
        "responses": {
          "200": {
            "description": ""
          }
        },
        "security": [
          {
            "bearer": []
          }
        ],
        "summary": "Ver meu customer",
        "tags": [
          "Customers"
        ]
      }
    },
    "/customers/{id}": {
      "get": {
        "operationId": "CustomersController_get",
        "parameters": [
          {
            "name": "id",
            "required": true,
            "in": "path",
            "schema": {
              "type": "string"
            }
          }
        ],
        "responses": {
          "200": {
            "description": ""
          }
        },
        "security": [
          {
            "bearer": []
          }
        ],
        "summary": "Ver customer por ID",
        "tags": [
          "Customers"
        ]
      },
      "patch": {
        "operationId": "CustomersController_update",
        "parameters": [
          {
            "name": "id",
            "required": true,
            "in": "path",
            "schema": {
              "type": "string"
            }
          }
        ],
        "requestBody": {
          "required": true,
          "content": {
            "application/json": {
              "schema": {
                "$ref": "#/components/schemas/UpdateCustomerLocalDto"
              }
            }
          }
        },
        "responses": {
          "200": {
            "description": ""
          }
        },
        "security": [
          {
            "bearer": []
          }
        ],
        "summary": "Atualizar customer",
        "tags": [
          "Customers"
        ]
      }
    },
    "/customers/{id}/balance": {
      "get": {
        "operationId": "CustomersController_balance",
        "parameters": [
          {
            "name": "id",
            "required": true,
            "in": "path",
            "schema": {
              "type": "string"
            }
          }
        ],
        "responses": {
          "200": {
            "description": ""
          }
        },
        "security": [
          {
            "bearer": []
          }
        ],
        "summary": "Saldo Pix do customer (soma dos depósitos Pix)",
        "tags": [
          "Customers"
        ]
      }
    },
    "/customers/{id}/statement": {
      "get": {
        "operationId": "CustomersController_statement",
        "parameters": [
          {
            "name": "id",
            "required": true,
            "in": "path",
            "schema": {
              "type": "string"
            }
          },
          {
            "name": "limit",
            "required": true,
            "in": "query",
            "schema": {
              "type": "string"
            }
          }
        ],
        "responses": {
          "200": {
            "description": ""
          }
        },
        "security": [
          {
            "bearer": []
          }
        ],
        "summary": "Extrato simplificado (delegar para statements)",
        "tags": [
          "Customers"
        ]
      }
    },
    "/customers/{id}/kyc/request": {
      "post": {
        "operationId": "CustomersController_requestKyc",
        "parameters": [
          {
            "name": "id",
            "required": true,
            "in": "path",
            "schema": {
              "type": "string"
            }
          }
        ],
        "responses": {
          "201": {
            "description": ""
          }
        },
        "security": [
          {
            "bearer": []
          }
        ],
        "summary": "Solicitar KYC",
        "tags": [
          "Customers"
        ]
      }
    },
    "/customers/{id}/kyc/review": {
      "patch": {
        "operationId": "CustomersController_review",
        "parameters": [
          {
            "name": "id",
            "required": true,
            "in": "path",
            "schema": {
              "type": "string"
            }
          }
        ],
        "responses": {
          "200": {
            "description": ""
          }
        },
        "security": [
          {
            "bearer": []
          }
        ],
        "summary": "Mover KYC para revisão",
        "tags": [
          "Customers"
        ]
      }
    },
    "/customers/{id}/kyc/approve": {
      "patch": {
        "operationId": "CustomersController_approve",
        "parameters": [
          {
            "name": "id",
            "required": true,
            "in": "path",
            "schema": {
              "type": "string"
            }
          }
        ],
        "responses": {
          "200": {
            "description": ""
          }
        },
        "security": [
          {
            "bearer": []
          }
        ],
        "summary": "Aprovar KYC",
        "tags": [
          "Customers"
        ]
      }
    },
    "/customers/{id}/kyc/reject": {
      "patch": {
        "operationId": "CustomersController_reject",
        "parameters": [
          {
            "name": "id",
            "required": true,
            "in": "path",
            "schema": {
              "type": "string"
            }
          }
        ],
        "responses": {
          "200": {
            "description": ""
          }
        },
        "security": [
          {
            "bearer": []
          }
        ],
        "summary": "Rejeitar KYC",
        "tags": [
          "Customers"
        ]
      }
    },
    "/statements/account-holders/{accountHolderId}/balance": {
      "get": {
        "operationId": "StatementsController_getBalance",
        "parameters": [
          {
            "name": "accountHolderId",
            "required": true,
            "in": "path",
            "schema": {
              "type": "string"
            }
          }
        ],
        "responses": {
          "200": {
            "description": ""
          }
        },
        "security": [
          {
            "bearer": []
          }
        ],
        "tags": [
          "Statements"
        ]
      }
    },
    "/statements/account-holders/{accountHolderId}": {
      "get": {
        "operationId": "StatementsController_getStatement",
        "parameters": [
          {
            "name": "accountHolderId",
            "required": true,
            "in": "path",
            "schema": {
              "type": "string"
            }
          },
          {
            "name": "from",
            "required": false,
            "in": "query",
            "description": "Data inicial (ISO 8601)",
            "schema": {
              "example": "2025-01-01T00:00:00.000Z",
              "type": "string"
            }
          },
          {
            "name": "to",
            "required": false,
            "in": "query",
            "description": "Data final (ISO 8601)",
            "schema": {
              "example": "2025-01-31T23:59:59.999Z",
              "type": "string"
            }
          },
          {
            "name": "startDate",
            "required": false,
            "in": "query",
            "description": "Alias para \"from\" (compatibilidade)",
            "schema": {
              "example": "2025-01-01",
              "type": "string"
            }
          },
          {
            "name": "endDate",
            "required": false,
            "in": "query",
            "description": "Alias para \"to\" (compatibilidade)",
            "schema": {
              "example": "2025-01-31",
              "type": "string"
            }
          },
          {
            "name": "type",
            "required": false,
            "in": "query",
            "description": "Tipo de transação",
            "schema": {
              "example": "PIX_IN",
              "type": "string",
              "enum": [
                "DEPOSIT",
                "WITHDRAW",
                "TRANSFER_IN",
                "TRANSFER_OUT",
                "PIX_IN",
                "PIX_OUT",
                "FEE",
                "REVERSAL"
              ]
            }
          },
          {
            "name": "status",
            "required": false,
            "in": "query",
            "description": "Status da transação",
            "schema": {
              "example": "COMPLETED",
              "type": "string",
              "enum": [
                "PENDING",
                "PROCESSING",
                "COMPLETED",
                "FAILED",
                "REVERSED",
                "CANCELED"
              ]
            }
          },
          {
            "name": "page",
            "required": false,
            "in": "query",
            "description": "Número da página",
            "schema": {
              "minimum": 1,
              "default": 1,
              "example": 1,
              "type": "number"
            }
          },
          {
            "name": "limit",
            "required": false,
            "in": "query",
            "description": "Limite de resultados por página",
            "schema": {
              "minimum": 1,
              "maximum": 200,
              "default": 50,
              "example": 50,
              "type": "number"
            }
          }
        ],
        "responses": {
          "200": {
            "description": ""
          }
        },
        "security": [
          {
            "bearer": []
          }
        ],
        "tags": [
          "Statements"
        ]
      }
    },
    "/statements": {
      "get": {
        "operationId": "StatementsController_myStatement",
        "parameters": [
          {
            "name": "from",
            "required": false,
            "in": "query",
            "description": "Data inicial (ISO 8601)",
            "schema": {
              "example": "2025-01-01T00:00:00.000Z",
              "type": "string"
            }
          },
          {
            "name": "to",
            "required": false,
            "in": "query",
            "description": "Data final (ISO 8601)",
            "schema": {
              "example": "2025-01-31T23:59:59.999Z",
              "type": "string"
            }
          },
          {
            "name": "startDate",
            "required": false,
            "in": "query",
            "description": "Alias para \"from\" (compatibilidade)",
            "schema": {
              "example": "2025-01-01",
              "type": "string"
            }
          },
          {
            "name": "endDate",
            "required": false,
            "in": "query",
            "description": "Alias para \"to\" (compatibilidade)",
            "schema": {
              "example": "2025-01-31",
              "type": "string"
            }
          },
          {
            "name": "type",
            "required": false,
            "in": "query",
            "description": "Tipo de transação",
            "schema": {
              "example": "PIX_IN",
              "type": "string",
              "enum": [
                "DEPOSIT",
                "WITHDRAW",
                "TRANSFER_IN",
                "TRANSFER_OUT",
                "PIX_IN",
                "PIX_OUT",
                "FEE",
                "REVERSAL"
              ]
            }
          },
          {
            "name": "status",
            "required": false,
            "in": "query",
            "description": "Status da transação",
            "schema": {
              "example": "COMPLETED",
              "type": "string",
              "enum": [
                "PENDING",
                "PROCESSING",
                "COMPLETED",
                "FAILED",
                "REVERSED",
                "CANCELED"
              ]
            }
          },
          {
            "name": "page",
            "required": false,
            "in": "query",
            "description": "Número da página",
            "schema": {
              "minimum": 1,
              "default": 1,
              "example": 1,
              "type": "number"
            }
          },
          {
            "name": "limit",
            "required": false,
            "in": "query",
            "description": "Limite de resultados por página",
            "schema": {
              "minimum": 1,
              "maximum": 200,
              "default": 50,
              "example": 50,
              "type": "number"
            }
          }
        ],
        "responses": {
          "200": {
            "description": ""
          }
        },
        "security": [
          {
            "bearer": []
          }
        ],
        "summary": "Extrato do customer logado",
        "tags": [
          "Statements"
        ]
      }
    },
    "/statements/admin/{customerId}": {
      "get": {
        "operationId": "StatementsController_byCustomerAdmin",
        "parameters": [
          {
            "name": "customerId",
            "required": true,
            "in": "path",
            "schema": {
              "type": "string"
            }
          },
          {
            "name": "from",
            "required": false,
            "in": "query",
            "description": "Data inicial (ISO 8601)",
            "schema": {
              "example": "2025-01-01T00:00:00.000Z",
              "type": "string"
            }
          },
          {
            "name": "to",
            "required": false,
            "in": "query",
            "description": "Data final (ISO 8601)",
            "schema": {
              "example": "2025-01-31T23:59:59.999Z",
              "type": "string"
            }
          },
          {
            "name": "startDate",
            "required": false,
            "in": "query",
            "description": "Alias para \"from\" (compatibilidade)",
            "schema": {
              "example": "2025-01-01",
              "type": "string"
            }
          },
          {
            "name": "endDate",
            "required": false,
            "in": "query",
            "description": "Alias para \"to\" (compatibilidade)",
            "schema": {
              "example": "2025-01-31",
              "type": "string"
            }
          },
          {
            "name": "type",
            "required": false,
            "in": "query",
            "description": "Tipo de transação",
            "schema": {
              "example": "PIX_IN",
              "type": "string",
              "enum": [
                "DEPOSIT",
                "WITHDRAW",
                "TRANSFER_IN",
                "TRANSFER_OUT",
                "PIX_IN",
                "PIX_OUT",
                "FEE",
                "REVERSAL"
              ]
            }
          },
          {
            "name": "status",
            "required": false,
            "in": "query",
            "description": "Status da transação",
            "schema": {
              "example": "COMPLETED",
              "type": "string",
              "enum": [
                "PENDING",
                "PROCESSING",
                "COMPLETED",
                "FAILED",
                "REVERSED",
                "CANCELED"
              ]
            }
          },
          {
            "name": "page",
            "required": false,
            "in": "query",
            "description": "Número da página",
            "schema": {
              "minimum": 1,
              "default": 1,
              "example": 1,
              "type": "number"
            }
          },
          {
            "name": "limit",
            "required": false,
            "in": "query",
            "description": "Limite de resultados por página",
            "schema": {
              "minimum": 1,
              "maximum": 200,
              "default": 50,
              "example": 50,
              "type": "number"
            }
          }
        ],
        "responses": {
          "200": {
            "description": ""
          }
        },
        "security": [
          {
            "bearer": []
          }
        ],
        "summary": "Extrato por customerId (Admin)",
        "tags": [
          "Statements"
        ]
      }
    },
    "/fdbank/system-health": {
      "get": {
        "operationId": "FdbankController_systemHealth",
        "parameters": [],
        "responses": {
          "200": {
            "description": ""
          }
        },
        "tags": [
          "Fdbank"
        ]
      }
    },
    "/fdbank/pix-keys": {
      "get": {
        "operationId": "FdbankPixKeyController_listPixKeys",
        "parameters": [],
        "responses": {
          "200": {
            "description": ""
          }
        },
        "tags": [
          "FdbankPixKey"
        ]
      },
      "post": {
        "operationId": "FdbankPixKeyController_createPixKey",
        "parameters": [],
        "responses": {
          "201": {
            "description": ""
          }
        },
        "tags": [
          "FdbankPixKey"
        ]
      }
    },
    "/fdbank/pix-keys/{id}": {
      "get": {
        "operationId": "FdbankPixKeyController_getPixKey",
        "parameters": [
          {
            "name": "id",
            "required": true,
            "in": "path",
            "schema": {
              "type": "string"
            }
          }
        ],
        "responses": {
          "200": {
            "description": ""
          }
        },
        "tags": [
          "FdbankPixKey"
        ]
      },
      "delete": {
        "operationId": "FdbankPixKeyController_deletePixKey",
        "parameters": [
          {
            "name": "id",
            "required": true,
            "in": "path",
            "schema": {
              "type": "string"
            }
          }
        ],
        "responses": {
          "200": {
            "description": ""
          }
        },
        "tags": [
          "FdbankPixKey"
        ]
      }
    },
    "/fdbank/pix-keys/resolve-dict": {
      "post": {
        "operationId": "FdbankPixKeyController_resolveDict",
        "parameters": [],
        "responses": {
          "201": {
            "description": ""
          }
        },
        "tags": [
          "FdbankPixKey"
        ]
      }
    },
    "/fdbank/bank-account/active": {
      "get": {
        "operationId": "FdbankBankAccountController_getActiveBankAccount",
        "parameters": [],
        "responses": {
          "200": {
            "description": ""
          }
        },
        "tags": [
          "FdbankBankAccount"
        ]
      }
    },
    "/fdbank/bank-account/statement": {
      "get": {
        "operationId": "FdbankBankAccountController_getBankAccountStatement",
        "parameters": [
          {
            "name": "startDate",
            "required": true,
            "in": "query",
            "schema": {
              "type": "string"
            }
          },
          {
            "name": "endDate",
            "required": true,
            "in": "query",
            "schema": {
              "type": "string"
            }
          },
          {
            "name": "page",
            "required": true,
            "in": "query",
            "schema": {
              "type": "number"
            }
          },
          {
            "name": "perPage",
            "required": true,
            "in": "query",
            "schema": {
              "type": "number"
            }
          }
        ],
        "responses": {
          "200": {
            "description": ""
          }
        },
        "tags": [
          "FdbankBankAccount"
        ]
      }
    },
    "/fdbank/customers": {
      "get": {
        "operationId": "FdbankCustomerController_listCustomers",
        "parameters": [],
        "responses": {
          "200": {
            "description": ""
          }
        },
        "tags": [
          "FdbankCustomer"
        ]
      },
      "post": {
        "operationId": "FdbankCustomerController_createCustomer",
        "parameters": [],
        "requestBody": {
          "required": true,
          "content": {
            "application/json": {
              "schema": {
                "$ref": "#/components/schemas/CreateCustomerDto"
              }
            }
          }
        },
        "responses": {
          "201": {
            "description": ""
          }
        },
        "tags": [
          "FdbankCustomer"
        ]
      }
    },
    "/fdbank/customers/{id}": {
      "get": {
        "operationId": "FdbankCustomerController_getCustomer",
        "parameters": [
          {
            "name": "id",
            "required": true,
            "in": "path",
            "schema": {
              "type": "string"
            }
          }
        ],
        "responses": {
          "200": {
            "description": ""
          }
        },
        "tags": [
          "FdbankCustomer"
        ]
      },
      "put": {
        "operationId": "FdbankCustomerController_updateCustomer",
        "parameters": [
          {
            "name": "id",
            "required": true,
            "in": "path",
            "schema": {
              "type": "string"
            }
          }
        ],
        "requestBody": {
          "required": true,
          "content": {
            "application/json": {
              "schema": {
                "$ref": "#/components/schemas/UpdateCustomerDto"
              }
            }
          }
        },
        "responses": {
          "200": {
            "description": ""
          }
        },
        "tags": [
          "FdbankCustomer"
        ]
      },
      "delete": {
        "operationId": "FdbankCustomerController_deleteCustomer",
        "parameters": [
          {
            "name": "id",
            "required": true,
            "in": "path",
            "schema": {
              "type": "string"
            }
          }
        ],
        "responses": {
          "200": {
            "description": ""
          }
        },
        "tags": [
          "FdbankCustomer"
        ]
      }
    },
    "/fdbank/pix-contacts": {
      "get": {
        "operationId": "FdbankPixContactController_listPixContacts",
        "parameters": [],
        "responses": {
          "200": {
            "description": ""
          }
        },
        "tags": [
          "FdbankPixContact"
        ]
      }
    },
    "/wallet/create-solana": {
      "post": {
        "operationId": "WalletController_createSolanaWalletForCustomer",
        "parameters": [],
        "responses": {
          "201": {
            "description": ""
          }
        },
        "tags": [
          "Wallet"
        ]
      }
    },
    "/wallet/solana-usdt-balance": {
      "get": {
        "operationId": "WalletController_getSolanaUsdtBalance",
        "parameters": [
          {
            "name": "address",
            "required": true,
            "in": "query",
            "schema": {
              "type": "string"
            }
          }
        ],
        "responses": {
          "200": {
            "description": ""
          }
        },
        "tags": [
          "Wallet"
        ]
      }
    },
    "/wallet/usdt": {
      "get": {
        "operationId": "WalletController_getAllUsdtWalletsForCustomer",
        "parameters": [],
        "responses": {
          "200": {
            "description": ""
          }
        },
        "tags": [
          "Wallet"
        ]
      }
    },
    "/wallet/teste-balance": {
      "get": {
        "operationId": "WalletController_getBalance",
        "parameters": [],
        "responses": {
          "200": {
            "description": ""
          }
        },
        "tags": [
          "Wallet"
        ]
      }
    },
    "/pix-keys/customer/{customerId}": {
      "get": {
        "operationId": "PixKeysController_getKeysByCustomer",
        "parameters": [
          {
            "name": "customerId",
            "required": true,
            "in": "path",
            "schema": {
              "type": "string"
            }
          }
        ],
        "responses": {
          "200": {
            "description": ""
          }
        },
        "tags": [
          "PixKeys"
        ]
      }
    },
    "/okx/balance-brl": {
      "get": {
        "operationId": "OkxController_getBrlBalance",
        "parameters": [],
        "responses": {
          "200": {
            "description": ""
          }
        },
        "tags": [
          "Okx"
        ]
      }
    },
    "/okx/balance-usdt": {
      "get": {
        "operationId": "OkxController_getUsdtBalance",
        "parameters": [],
        "responses": {
          "200": {
            "description": ""
          }
        },
        "tags": [
          "Okx"
        ]
      }
    },
    "/okx/buy-and-check-history": {
      "post": {
        "operationId": "OkxController_buyAndCheckHistory",
        "parameters": [],
        "responses": {
          "201": {
            "description": ""
          }
        },
        "tags": [
          "Okx"
        ]
      }
    },
    "/okx/withdraw-usdt": {
      "post": {
        "operationId": "OkxController_safeWithdrawUsdt",
        "parameters": [],
        "responses": {
          "201": {
            "description": ""
          }
        },
        "tags": [
          "Okx"
        ]
      }
    },
    "/admin/dashboard/stats": {
      "get": {
        "operationId": "AdminDashboardController_stats",
        "parameters": [],
        "responses": {
          "200": {
            "description": "OK"
          }
        },
        "security": [
          {
            "bearer": []
          }
        ],
        "summary": "Dashboard completo",
        "tags": [
          "Admin Dashboard"
        ]
      }
    },
    "/admin/dashboard/summary": {
      "get": {
        "operationId": "AdminDashboardController_summary",
        "parameters": [],
        "responses": {
          "200": {
            "description": "OK"
          }
        },
        "security": [
          {
            "bearer": []
          }
        ],
        "summary": "Resumo geral",
        "tags": [
          "Admin Dashboard"
        ]
      }
    },
    "/admin/dashboard/inter-balance": {
      "get": {
        "operationId": "AdminDashboardController_interBalance",
        "parameters": [],
        "responses": {
          "200": {
            "description": "OK"
          },
          "503": {
            "description": "Serviço não disponível"
          }
        },
        "security": [
          {
            "bearer": []
          }
        ],
        "summary": "Saldo Inter",
        "tags": [
          "Admin Dashboard"
        ]
      }
    },
    "/admin/dashboard/latest-users": {
      "get": {
        "operationId": "AdminDashboardController_latestUsers",
        "parameters": [],
        "responses": {
          "200": {
            "description": "OK"
          }
        },
        "security": [
          {
            "bearer": []
          }
        ],
        "summary": "Últimos usuários",
        "tags": [
          "Admin Dashboard"
        ]
      }
    },
    "/admin/dashboard/latest-transactions": {
      "get": {
        "operationId": "AdminDashboardController_latestTransactions",
        "parameters": [],
        "responses": {
          "200": {
            "description": "OK"
          }
        },
        "security": [
          {
            "bearer": []
          }
        ],
        "summary": "Últimas transações",
        "tags": [
          "Admin Dashboard"
        ]
      }
    },
    "/inter/webhooks/{tipoWebhook}/callbacks": {
      "get": {
        "operationId": "InterWebhookController_getCallbacks",
        "parameters": [
          {
            "name": "tipoWebhook",
            "required": true,
            "in": "path",
            "description": "Tipo do webhook",
            "schema": {
              "enum": [
                "pix",
                "boletos"
              ],
              "type": "string"
            }
          }
        ],
        "responses": {
          "200": {
            "description": "Callbacks encontrados"
          }
        },
        "security": [
          {
            "bearer": []
          }
        ],
        "summary": "📋 Consultar callbacks cadastrados",
        "tags": [
          "🔔 Webhooks (Inter)"
        ]
      },
      "post": {
        "operationId": "InterWebhookController_createCallback",
        "parameters": [
          {
            "name": "tipoWebhook",
            "required": true,
            "in": "path",
            "schema": {
              "enum": [
                "pix",
                "boletos"
              ],
              "type": "string"
            }
          }
        ],
        "requestBody": {
          "required": true,
          "content": {
            "application/json": {
              "schema": {
                "$ref": "#/components/schemas/CreateWebhookCallbackDto"
              }
            }
          }
        },
        "responses": {
          "201": {
            "description": "Callback criado com sucesso"
          }
        },
        "security": [
          {
            "bearer": []
          }
        ],
        "summary": "➕ Criar callback",
        "tags": [
          "🔔 Webhooks (Inter)"
        ]
      },
      "put": {
        "operationId": "InterWebhookController_updateCallback",
        "parameters": [
          {
            "name": "tipoWebhook",
            "required": true,
            "in": "path",
            "schema": {
              "enum": [
                "pix",
                "boletos"
              ],
              "type": "string"
            }
          }
        ],
        "requestBody": {
          "required": true,
          "content": {
            "application/json": {
              "schema": {
                "$ref": "#/components/schemas/UpdateWebhookCallbackDto"
              }
            }
          }
        },
        "responses": {
          "200": {
            "description": "Callback atualizado"
          }
        },
        "security": [
          {
            "bearer": []
          }
        ],
        "summary": "✏️ Atualizar callback",
        "tags": [
          "🔔 Webhooks (Inter)"
        ]
      },
      "delete": {
        "operationId": "InterWebhookController_deleteCallback",
        "parameters": [
          {
            "name": "tipoWebhook",
            "required": true,
            "in": "path",
            "schema": {
              "enum": [
                "pix",
                "boletos"
              ],
              "type": "string"
            }
          }
        ],
        "responses": {
          "200": {
            "description": "Callback excluído"
          }
        },
        "security": [
          {
            "bearer": []
          }
        ],
        "summary": "🗑️ Excluir callback",
        "tags": [
          "🔔 Webhooks (Inter)"
        ]
      }
    },
    "/inter/webhooks/receive/pix": {
      "post": {
        "description": "Endpoint chamado automaticamente pelo Banco Inter quando um Pix é recebido",
        "operationId": "InterWebhookController_handlePixWebhook",
        "parameters": [
          {
            "name": "x-inter-signature",
            "in": "header",
            "description": "Assinatura HMAC SHA256 do webhook",
            "required": false,
            "schema": {
              "type": "string"
            }
          }
        ],
        "responses": {
          "200": {
            "description": "Webhook processado com sucesso",
            "content": {
              "application/json": {
                "schema": {
                  "example": {
                    "success": true,
                    "message": "Webhook processado",
                    "processedAt": "2025-11-13T16:00:00.000Z"
                  }
                }
              }
            }
          },
          "400": {
            "description": "Erro ao processar webhook"
          }
        },
        "summary": "💰 Receber webhook de Pix (Público)",
        "tags": [
          "🔔 Webhooks (Inter)"
        ]
      }
    },
    "/inter/webhooks/receive/boletos": {
      "post": {
        "description": "Endpoint chamado automaticamente pelo Banco Inter quando há alteração em boleto",
        "operationId": "InterWebhookController_handleBoletoWebhook",
        "parameters": [
          {
            "name": "x-inter-signature",
            "in": "header",
            "description": "Assinatura HMAC SHA256",
            "required": false,
            "schema": {
              "type": "string"
            }
          }
        ],
        "responses": {
          "200": {
            "description": "Webhook processado"
          }
        },
        "summary": "📄 Receber webhook de Boleto (Público)",
        "tags": [
          "🔔 Webhooks (Inter)"
        ]
      }
    },
    "/inter/webhooks/test/{tipoWebhook}": {
      "post": {
        "operationId": "InterWebhookController_testWebhook",
        "parameters": [
          {
            "name": "tipoWebhook",
            "required": true,
            "in": "path",
            "description": "Tipo do webhook para testar",
            "schema": {
              "enum": [
                "pix",
                "boletos"
              ],
              "type": "string"
            }
          }
        ],
        "responses": {
          "200": {
            "description": "Teste executado com sucesso",
            "content": {
              "application/json": {
                "schema": {
                  "example": {
                    "success": true,
                    "message": "Webhook Pix de teste processado",
                    "payload": {
                      "pix": [
                        {
                          "e2eId": "E1731512345TEST",
                          "txid": "TEST-1731512345",
                          "valor": 100.5,
                          "horario": "2025-11-13T16:00:00.000Z"
                        }
                      ]
                    }
                  }
                }
              }
            }
          }
        },
        "security": [
          {
            "bearer": []
          }
        ],
        "summary": "🧪 Testar webhook manualmente",
        "tags": [
          "🔔 Webhooks (Inter)"
        ]
      }
    },
    "/inter/webhooks/logs": {
      "get": {
        "operationId": "InterWebhookController_getLogs",
        "parameters": [],
        "responses": {
          "200": {
            "description": "Logs encontrados"
          }
        },
        "security": [
          {
            "bearer": []
          }
        ],
        "summary": "📊 Ver logs de webhooks",
        "tags": [
          "🔔 Webhooks (Inter)"
        ]
      }
    },
    "/inter/webhooks/logs/{id}": {
      "get": {
        "operationId": "InterWebhookController_getLogDetails",
        "parameters": [
          {
            "name": "id",
            "required": true,
            "in": "path",
            "description": "ID do log",
            "schema": {
              "type": "string"
            }
          }
        ],
        "responses": {
          "200": {
            "description": "Log encontrado"
          },
          "404": {
            "description": "Log não encontrado"
          }
        },
        "security": [
          {
            "bearer": []
          }
        ],
        "summary": "🔍 Ver detalhes do log",
        "tags": [
          "🔔 Webhooks (Inter)"
        ]
      }
    },
    "/inter/webhooks/health": {
      "get": {
        "operationId": "InterWebhookController_healthCheck",
        "parameters": [],
        "responses": {
          "200": {
            "description": "Status do sistema"
          }
        },
        "summary": "💚 Health check dos webhooks",
        "tags": [
          "🔔 Webhooks (Inter)"
        ]
      }
    },
    "/inter/pix/keys/random": {
      "post": {
        "operationId": "InterPixKeysController_registerRandomKey",
        "parameters": [],
        "responses": {
          "201": {
            "description": "Chave Pix criada com sucesso"
          }
        },
        "security": [
          {
            "bearer": []
          }
        ],
        "summary": "Cadastrar chave Pix aleatória para o customer logado",
        "tags": [
          "Inter - Pix Keys"
        ]
      }
    },
    "/inter/pix/keys": {
      "post": {
        "operationId": "InterPixKeysController_registerKey",
        "parameters": [],
        "requestBody": {
          "required": true,
          "content": {
            "application/json": {
              "schema": {
                "$ref": "#/components/schemas/RegisterPixKeyDto"
              }
            }
          }
        },
        "responses": {
          "201": {
            "description": "Chave Pix cadastrada com sucesso"
          }
        },
        "security": [
          {
            "bearer": []
          }
        ],
        "summary": "Cadastrar chave Pix específica (CPF, Email, Telefone)",
        "tags": [
          "Inter - Pix Keys"
        ]
      },
      "get": {
        "operationId": "InterPixKeysController_listKeys",
        "parameters": [],
        "responses": {
          "200": {
            "description": ""
          }
        },
        "security": [
          {
            "bearer": []
          }
        ],
        "summary": "Listar todas as chaves Pix cadastradas (Admin)",
        "tags": [
          "Inter - Pix Keys"
        ]
      }
    },
    "/inter/pix/keys/{chave}": {
      "get": {
        "operationId": "InterPixKeysController_getKey",
        "parameters": [
          {
            "name": "chave",
            "required": true,
            "in": "path",
            "schema": {
              "example": "12345678901",
              "type": "string"
            }
          }
        ],
        "responses": {
          "200": {
            "description": ""
          }
        },
        "security": [
          {
            "bearer": []
          }
        ],
        "summary": "Consultar chave Pix específica (Admin)",
        "tags": [
          "Inter - Pix Keys"
        ]
      },
      "delete": {
        "operationId": "InterPixKeysController_deleteKey",
        "parameters": [
          {
            "name": "chave",
            "required": true,
            "in": "path",
            "schema": {
              "example": "12345678901",
              "type": "string"
            }
          }
        ],
        "responses": {
          "200": {
            "description": ""
          }
        },
        "security": [
          {
            "bearer": []
          }
        ],
        "summary": "Excluir chave Pix (Admin)",
        "tags": [
          "Inter - Pix Keys"
        ]
      }
    },
    "/inter/pix/keys/{chave}/available": {
      "get": {
        "operationId": "InterPixKeysController_checkAvailability",
        "parameters": [
          {
            "name": "chave",
            "required": true,
            "in": "path",
            "schema": {
              "example": "12345678901",
              "type": "string"
            }
          }
        ],
        "responses": {
          "200": {
            "description": ""
          }
        },
        "security": [
          {
            "bearer": []
          }
        ],
        "summary": "Verificar se chave Pix está disponível",
        "tags": [
          "Inter - Pix Keys"
        ]
      }
    },
    "/inter/test/auth": {
      "get": {
        "operationId": "InterTestController_testAuth",
        "parameters": [],
        "responses": {
          "200": {
            "description": ""
          }
        },
        "security": [
          {
            "bearer": []
          }
        ],
        "summary": "🔐 Testar autenticação OAuth 2.0 (Admin)",
        "tags": [
          "Inter - Testes"
        ]
      }
    },
    "/inter/test/saldo": {
      "get": {
        "operationId": "InterTestController_testSaldo",
        "parameters": [],
        "responses": {
          "200": {
            "description": ""
          }
        },
        "security": [
          {
            "bearer": []
          }
        ],
        "summary": "💰 Testar consulta de saldo (Admin)",
        "tags": [
          "Inter - Testes"
        ]
      }
    },
    "/inter/test/extrato": {
      "get": {
        "operationId": "InterTestController_testExtrato",
        "parameters": [],
        "responses": {
          "200": {
            "description": ""
          }
        },
        "security": [
          {
            "bearer": []
          }
        ],
        "summary": "📊 Testar consulta de extrato (Admin)",
        "tags": [
          "Inter - Testes"
        ]
      }
    },
    "/inter/test/pix/chaves": {
      "get": {
        "operationId": "InterTestController_testPixKeys",
        "parameters": [],
        "responses": {
          "200": {
            "description": ""
          }
        },
        "security": [
          {
            "bearer": []
          }
        ],
        "summary": "🔑 Testar listagem de chaves Pix (Admin)",
        "tags": [
          "Inter - Testes"
        ]
      }
    },
    "/inter/test/pix/chave-teste": {
      "post": {
        "operationId": "InterTestController_testCreatePixKey",
        "parameters": [],
        "responses": {
          "201": {
            "description": ""
          }
        },
        "security": [
          {
            "bearer": []
          }
        ],
        "summary": "🔑 Criar chave Pix aleatória de teste (Admin)",
        "tags": [
          "Inter - Testes"
        ]
      }
    },
    "/inter/test/connection": {
      "get": {
        "operationId": "InterTestController_testConnection",
        "parameters": [],
        "responses": {
          "200": {
            "description": ""
          }
        },
        "security": [
          {
            "bearer": []
          }
        ],
        "summary": "🌐 Testar conexão geral com API Inter (Admin)",
        "tags": [
          "Inter - Testes"
        ]
      }
    },
    "/inter/test/health": {
      "get": {
        "operationId": "InterTestController_healthCheck",
        "parameters": [],
        "responses": {
          "200": {
            "description": ""
          }
        },
        "security": [
          {
            "bearer": []
          }
        ],
        "summary": "❤️ Health check da integração Inter (Admin)",
        "tags": [
          "Inter - Testes"
        ]
      }
    },
    "/inter/test/token-info": {
      "get": {
        "operationId": "InterTestController_getTokenInfo",
        "parameters": [],
        "responses": {
          "200": {
            "description": ""
          }
        },
        "security": [
          {
            "bearer": []
          }
        ],
        "summary": "🔍 Verificar informações do token OAuth (Admin)",
        "tags": [
          "Inter - Testes"
        ]
      }
    },
    "/inter/banking/saldo": {
      "get": {
        "operationId": "InterBankingController_getSaldo",
        "parameters": [],
        "responses": {
          "200": {
            "description": ""
          }
        },
        "security": [
          {
            "bearer": []
          }
        ],
        "summary": "Consultar saldo da conta Inter (Admin)",
        "tags": [
          "Inter - Banking"
        ]
      }
    },
    "/inter/banking/extrato": {
      "get": {
        "operationId": "InterBankingController_getExtrato",
        "parameters": [
          {
            "name": "dataInicio",
            "required": false,
            "in": "query",
            "schema": {
              "example": "2025-11-01",
              "type": "string"
            }
          },
          {
            "name": "dataFim",
            "required": false,
            "in": "query",
            "schema": {
              "example": "2025-11-12",
              "type": "string"
            }
          },
          {
            "name": "dias",
            "required": false,
            "in": "query",
            "schema": {
              "example": 30,
              "type": "string"
            }
          }
        ],
        "responses": {
          "200": {
            "description": ""
          }
        },
        "security": [
          {
            "bearer": []
          }
        ],
        "summary": "Consultar extrato (Admin)",
        "tags": [
          "Inter - Banking"
        ]
      }
    },
    "/inter/pix/send-pix": {
      "post": {
        "operationId": "InterPixController_sendPix",
        "parameters": [],
        "requestBody": {
          "required": true,
          "content": {
            "application/json": {
              "schema": {
                "$ref": "#/components/schemas/SendPixDto"
              }
            }
          }
        },
        "responses": {
          "201": {
            "description": "Pix enviado com sucesso",
            "content": {
              "application/json": {
                "schema": {
                  "$ref": "#/components/schemas/PixPaymentResponseDto"
                }
              }
            }
          },
          "400": {
            "description": "Saldo insuficiente ou dados inválidos"
          }
        },
        "security": [
          {
            "bearer": []
          }
        ],
        "summary": "💸 Enviar Pix",
        "tags": [
          "💸 Pix (Inter)"
        ]
      }
    },
    "/inter/pix/status/{endToEndId}": {
      "get": {
        "operationId": "InterPixController_getPixStatus",
        "parameters": [
          {
            "name": "endToEndId",
            "required": true,
            "in": "path",
            "schema": {
              "type": "string"
            }
          }
        ],
        "responses": {
          "200": {
            "description": ""
          }
        },
        "security": [
          {
            "bearer": []
          }
        ],
        "summary": "🔍 Consultar status de Pix enviado",
        "tags": [
          "💸 Pix (Inter)"
        ]
      }
    },
    "/inter/pix/cobrancas": {
      "post": {
        "operationId": "InterPixController_createCobranca",
        "parameters": [],
        "requestBody": {
          "required": true,
          "content": {
            "application/json": {
              "schema": {
                "$ref": "#/components/schemas/CreatePixChargeDto"
              }
            }
          }
        },
        "responses": {
          "201": {
            "description": ""
          }
        },
        "security": [
          {
            "bearer": []
          }
        ],
        "summary": "📱 Criar cobrança Pix (QR Code)",
        "tags": [
          "💸 Pix (Inter)"
        ]
      }
    },
    "/inter/pix/cobrancas/{txid}": {
      "get": {
        "operationId": "InterPixController_getCobranca",
        "parameters": [
          {
            "name": "txid",
            "required": true,
            "in": "path",
            "schema": {
              "type": "string"
            }
          }
        ],
        "responses": {
          "200": {
            "description": ""
          }
        },
        "security": [
          {
            "bearer": []
          }
        ],
        "summary": "🔍 Consultar cobrança Pix",
        "tags": [
          "💸 Pix (Inter)"
        ]
      }
    },
    "/inter/pix/testar-envio": {
      "post": {
        "operationId": "InterPixController_testarEnvioPix",
        "parameters": [
          {
            "name": "idIdempotente",
            "required": true,
            "in": "query",
            "schema": {
              "type": "string"
            }
          }
        ],
        "responses": {
          "201": {
            "description": ""
          }
        },
        "security": [
          {
            "bearer": []
          }
        ],
        "summary": "🔬 Testar envio Pix (direto para Inter)",
        "tags": [
          "💸 Pix (Inter)"
        ]
      }
    },
    "/payments": {
      "get": {
        "operationId": "PaymentsController_listPayments",
        "parameters": [
          {
            "name": "customerId",
            "required": true,
            "in": "query",
            "schema": {
              "type": "string"
            }
          },
          {
            "name": "dataInicio",
            "required": true,
            "in": "query",
            "schema": {
              "type": "string"
            }
          },
          {
            "name": "dataFim",
            "required": true,
            "in": "query",
            "schema": {
              "type": "string"
            }
          }
        ],
        "responses": {
          "200": {
            "description": ""
          }
        },
        "tags": [
          "Payments"
        ]
      }
    },
    "/payments/pix/send": {
      "post": {
        "operationId": "PaymentsController_sendPix",
        "parameters": [],
        "requestBody": {
          "required": true,
          "content": {
            "application/json": {
              "schema": {
                "$ref": "#/components/schemas/SendPixDto"
              }
            }
          }
        },
        "responses": {
          "201": {
            "description": ""
          }
        },
        "tags": [
          "Payments"
        ]
      }
    },
    "/transactions/{id}": {
      "get": {
        "operationId": "TransactionsController_findOne",
        "parameters": [
          {
            "name": "id",
            "required": true,
            "in": "path",
            "schema": {
              "example": "tx-uuid",
              "type": "string"
            }
          }
        ],
        "responses": {
          "200": {
            "description": ""
          }
        },
        "security": [
          {
            "bearer": []
          }
        ],
        "summary": "Buscar transação por ID",
        "tags": [
          "Transactions"
        ]
      }
    },
    "/transactions/{id}/reverse": {
      "post": {
        "operationId": "TransactionsController_reverse",
        "parameters": [
          {
            "name": "id",
            "required": true,
            "in": "path",
            "schema": {
              "example": "tx-uuid",
              "type": "string"
            }
          }
        ],
        "responses": {
          "201": {
            "description": ""
          }
        },
        "security": [
          {
            "bearer": []
          }
        ],
        "summary": "Reverter transação (Admin apenas)",
        "tags": [
          "Transactions"
        ]
      }
    }
  },
  "info": {
    "title": "OTSEM API",
    "description": "Documentação completa das rotas da OTSEM API",
    "version": "1.0.0",
    "contact": {}
  },
  "tags": [],
  "servers": [],
  "components": {
    "securitySchemes": {
      "bearer": {
        "scheme": "bearer",
        "bearerFormat": "JWT",
        "type": "http"
      }
    },
    "schemas": {
      "RegisterDto": {
        "type": "object",
        "properties": {}
      },
      "ForgotPasswordDto": {
        "type": "object",
        "properties": {}
      },
      "ResetPasswordDto": {
        "type": "object",
        "properties": {}
      },
      "UpdateUserDto": {
        "type": "object",
        "properties": {}
      },
      "ChangePasswordDto": {
        "type": "object",
        "properties": {}
      },
      "AddressDto": {
        "type": "object",
        "properties": {}
      },
      "CreateCustomerLocalDto": {
        "type": "object",
        "properties": {
          "type": {
            "type": "string",
            "enum": [
              "PF",
              "PJ"
            ],
            "example": "PF"
          },
          "name": {
            "type": "string",
            "example": "João Silva"
          },
          "email": {
            "type": "string",
            "example": "joao@email.com"
          },
          "phone": {
            "type": "string",
            "example": "+5511999999999"
          },
          "cpf": {
            "type": "string",
            "example": "12345678901"
          },
          "birthday": {
            "type": "string",
            "example": "1990-01-15"
          },
          "rg": {
            "type": "string",
            "example": "123456789"
          },
          "mothersName": {
            "type": "string",
            "example": "João Silva"
          },
          "cnpj": {
            "type": "string",
            "example": "12345678000190"
          },
          "companyName": {
            "type": "string",
            "example": "Empresa LTDA"
          },
          "tradingName": {
            "type": "string",
            "example": "Empresa"
          },
          "foundingDate": {
            "type": "string",
            "example": "2020-01-01"
          },
          "address": {
            "$ref": "#/components/schemas/AddressDto"
          },
          "metadata": {
            "type": "object",
            "example": {
              "referralCode": "XYZ123"
            }
          }
        },
        "required": [
          "type",
          "name",
          "email"
        ]
      },
      "UpdateCustomerLocalDto": {
        "type": "object",
        "properties": {
          "name": {
            "type": "string",
            "example": "João Silva"
          },
          "email": {
            "type": "string",
            "example": "joao@email.com"
          },
          "phone": {
            "type": "string",
            "example": "+5511999999999"
          },
          "birthday": {
            "type": "string",
            "example": "1990-01-15"
          },
          "rg": {
            "type": "string",
            "example": "123456789"
          },
          "mothersName": {
            "type": "string",
            "example": "João Silva"
          },
          "companyName": {
            "type": "string",
            "example": "Empresa LTDA"
          },
          "tradingName": {
            "type": "string",
            "example": "Empresa"
          },
          "foundingDate": {
            "type": "string",
            "example": "2020-01-01"
          },
          "address": {
            "$ref": "#/components/schemas/AddressDto"
          },
          "metadata": {
            "type": "object",
            "example": {
              "referralCode": "XYZ123"
            }
          },
          "accountStatus": {
            "type": "string",
            "enum": [
              "not_requested",
              "requested",
              "in_review",
              "approved",
              "rejected",
              "suspended"
            ]
          }
        }
      },
      "CreateCustomerDto": {
        "type": "object",
        "properties": {}
      },
      "UpdateCustomerDto": {
        "type": "object",
        "properties": {}
      },
      "CreateWebhookCallbackDto": {
        "type": "object",
        "properties": {
          "webhookUrl": {
            "type": "string",
            "description": "URL do callback (deve ser HTTPS)",
            "example": "https://api.otsembank.com/inter/webhooks/receive/pix"
          }
        },
        "required": [
          "webhookUrl"
        ]
      },
      "UpdateWebhookCallbackDto": {
        "type": "object",
        "properties": {
          "webhookUrl": {
            "type": "string",
            "description": "Nova URL do callback (deve ser HTTPS)",
            "example": "https://api.otsembank.com/inter/webhooks/receive/pix"
          }
        },
        "required": [
          "webhookUrl"
        ]
      },
      "RegisterPixKeyDto": {
        "type": "object",
        "properties": {
          "tipoChave": {
            "type": "string",
            "enum": [
              "CPF",
              "CNPJ",
              "EMAIL",
              "TELEFONE",
              "ALEATORIA"
            ],
            "example": "CPF",
            "description": "Tipo da chave Pix"
          },
          "chave": {
            "type": "string",
            "example": "12345678901",
            "description": "Valor da chave (obrigatório para CPF, CNPJ, EMAIL, TELEFONE)"
          }
        },
        "required": [
          "tipoChave"
        ]
      },
      "SendPixDto": {
        "type": "object",
        "properties": {
          "valor": {
            "type": "number",
            "example": 100.5,
            "description": "Valor em reais",
            "minimum": 0.01
          },
          "chaveDestino": {
            "type": "string",
            "example": "12345678900",
            "description": "Chave Pix do destinatário"
          },
          "tipoChave": {
            "type": "string",
            "enum": [
              "CPF",
              "CNPJ",
              "EMAIL",
              "TELEFONE",
              "CHAVE_ALEATORIA",
              "CHAVE"
            ],
            "example": "CPF",
            "description": "Tipo da chave Pix"
          },
          "descricao": {
            "type": "string",
            "example": "Pagamento de serviço",
            "description": "Descrição (máximo 140 caracteres)",
            "maxLength": 140
          },
          "nomeFavorecido": {
            "type": "string",
            "example": "João Silva",
            "description": "Nome do favorecido (opcional)"
          }
        },
        "required": [
          "valor",
          "chaveDestino",
          "tipoChave"
        ]
      },
      "PixPaymentResponseDto": {
        "type": "object",
        "properties": {
          "endToEndId": {
            "type": "string",
            "example": "E123456789012345678901234567890AB"
          },
          "valor": {
            "type": "number",
            "example": 100.5
          },
          "horario": {
            "type": "string",
            "example": "2025-11-13T14:30:00Z"
          },
          "status": {
            "type": "string",
            "example": "PROCESSANDO"
          },
          "transacaoId": {
            "type": "string",
            "example": "abc123"
          }
        },
        "required": [
          "endToEndId",
          "valor",
          "horario",
          "status",
          "transacaoId"
        ]
      },
      "CreatePixChargeDto": {
        "type": "object",
        "properties": {
          "valor": {
            "type": "number",
            "example": 100.5,
            "description": "Valor da cobrança"
          },
          "expiracao": {
            "type": "number",
            "example": 3600,
            "description": "Tempo de expiração em segundos (padrão: 1 hora)"
          },
          "descricao": {
            "type": "string",
            "example": "Pagamento de serviço",
            "description": "Descrição da cobrança"
          }
        },
        "required": [
          "valor"
        ]
      }
    }
  }
}